parking_utils_aec/__init__.py
parking_utils_aec/parking_utils.py
parking_utils_aec-0.1.7.dist-info/LICENSE
parking_utils_aec-0.1.7.dist-info/METADATA
parking_utils_aec-0.1.7.dist-info/WHEEL
parking_utils_aec-0.1.7.dist-info/top_level.txt
parking_utils_aec-0.1.7.dist-info/RECORD
